turpy/__init__.py
turpy/_types.py
turpy/base.py
turpy/augmentation/__init__.py
turpy/augmentation/_eda_augmentator.py
turpy/augmentation/_keyboard_augmentator.py
turpy/models/__init__.py
turpy/models/_deep.py
turpy/models/_doc2vec.py
turpy/models/_tfidf.py
turpy/preprocess/__init__.py
turpy/preprocess/_spelling_preprocessor.py
turpy/preprocess/_text_preprocessor.py
turpy/resources/__init__.py
turpy/resources/qwerty_maps.json
turpy/resources/stopwords.txt
turpy/resources/turkish_finite_state_machine.xml
turpy/resources/word_count.txt
turpy/resources/word_count_v2.csv
turpy/tests/__init__.py
turpy/tests/test_augmentation.py
turpy/tests/test_models.py
turpy/tests/test_preprocess.py
turpy/visualization/__init__.py
turpy/visualization/_wordcloud.py
turpy_nlpkit-0.1.0.dist-info/LICENSE
turpy_nlpkit-0.1.0.dist-info/METADATA
turpy_nlpkit-0.1.0.dist-info/WHEEL
turpy_nlpkit-0.1.0.dist-info/top_level.txt
turpy_nlpkit-0.1.0.dist-info/RECORD
